podscan_api/__init__.py
podscan_api/client.py
podscan_api/exceptions.py
podscan_api/http_client.py
podscan_api/version.py
podscan_api/resources/__init__.py
podscan_api/resources/alerts.py
podscan_api/resources/categories.py
podscan_api/resources/episodes.py
podscan_api/resources/podcasts.py
podscan_api/resources/teams.py
tests/__init__.py
tests/test_alerts.py
tests/test_categories.py
tests/test_client.py
tests/test_episodes.py
tests/test_podcasts.py
podscan_api-0.1.0.dist-info/LICENSE
podscan_api-0.1.0.dist-info/METADATA
podscan_api-0.1.0.dist-info/WHEEL
podscan_api-0.1.0.dist-info/top_level.txt
podscan_api-0.1.0.dist-info/RECORD
