Metadata-Version: 2.1
Name: podscan_api
Version: 0.1.0
Summary: A Python client for interacting with the Podscan.fm API
Home-page: https://github.com/agorasecurity/podscan
Author: AgoraSecurity
Author-email: posdscan-python@agora-security.com
Classifier: Development Status :: 3 - Alpha
Classifier: Intended Audience :: Developers
Classifier: License :: OSI Approved :: MIT License
Classifier: Programming Language :: Python :: 3
Classifier: Programming Language :: Python :: 3.6
Classifier: Programming Language :: Python :: 3.7
Classifier: Programming Language :: Python :: 3.8
Classifier: Programming Language :: Python :: 3.9
License-File: LICENSE
Requires-Dist: requests
Requires-Dist: python-dotenv
